{"levelID":22,"levelName":"Level 22","wasCompleted":false,"collectablesObtained":0,"collectablesTotal":9,"subLevelData":[{"playerData":[{"currentGravity":[0.0,-1.0],"position":[-57.5999908447266,-102.399871826172,0.0],"rotation":[0.0,0.0,0.0,1.0]}],"tileData":[{"destroyable":false,"alone":false,"emissionUpEnabled":false,"emissionRightEnabled":true,"emissionLeftEnabled":true,"emissionDownEnabled":false,"position":[-112.0,-86.3998870849609,0.0],"rotation":[0.0,0.0,0.0,1.0]},{"destroyable":false,"alone":false,"emissionUpEnabled":false,"emissionRightEnabled":true,"emissionLeftEnabled":true,"emissionDownEnabled":false,"position":[-112.0,-89.5998840332031,0.0],"rotation":[0.0,0.0,0.0,1.0]},{"destroyable":false,"alone":false,"emissionUpEnabled":false,"emissionRightEnabled":true,"emissionLeftEnabled":true,"emissionDownEnabled":false,"position":[-112.0,-92.7998809814453,0.0],"rotation":[0.0,0.0,0.0,1.0]},{"destroyable":false,"alone":false,"emissionUpEnabled":false,"emissionRightEnabled":true,"emissionLeftEnabled":true,"emissionDownEnabled":false,"position":[-112.0,-95.9998779296875,0.0],"rotation":[0.0,0.0,0.0,1.0]},{"destroyable":false,"alone":false,"emissionUpEnabled":false,"emissionRightEnabled":true,"emissionLeftEnabled":true,"emissionDownEnabled":false,"position":[-112.0,-99.1998748779297,0.0],"rotation":[0.0,0.0,0.0,1.0]},{"destroyable":false,"alone":false,"emissionUpEnabled":false,"emissionRightEnabled":true,"emissionLeftEnabled":true,"emissionDownEnabled":false,"position":[-112.0,-102.399871826172,0.0],"rotation":[0.0,0.0,0.0,1.0]},{"destroyable":false,"alone":false,"emissionUpEnabled":false,"emissionRightEnabled":false,"emissionLeftEnabled":true,"emissionDownEnabled":true,"position":[-112.0,-105.599868774414,0.0],"rotation":[0.0,0.0,0.0,1.0]},{"destroyable":false,"alone":false,"emissionUpEnabled":true,"emissionRightEnabled":false,"emissionLeftEnabled":false,"emissionDownEnabled":true,"position":[-108.800003051758,-105.599868774414,0.0],"rotation":[0.0,0.0,0.0,1.0]},{"destroyable":false,"alone":false,"emissionUpEnabled":true,"emissionRightEnabled":false,"emissionLeftEnabled":false,"emissionDownEnabled":true,"position":[-105.599998474121,-105.599868774414,0.0],"rotation":[0.0,0.0,0.0,1.0]},{"destroyable":false,"alone":false,"emissionUpEnabled":true,"emissionRightEnabled":false,"emissionLeftEnabled":false,"emissionDownEnabled":true,"position":[-102.400001525879,-105.599868774414,0.0],"rotation":[0.0,0.0,0.0,1.0]},{"destroyable":false,"alone":false,"emissionUpEnabled":true,"emissionRightEnabled":false,"emissionLeftEnabled":false,"emissionDownEnabled":true,"position":[-99.1999969482422,-105.599868774414,0.0],"rotation":[0.0,0.0,0.0,1.0]},{"destroyable":false,"alone":false,"emissionUpEnabled":true,"emissionRightEnabled":false,"emissionLeftEnabled":false,"emissionDownEnabled":true,"position":[-96.0,-105.599868774414,0.0],"rotation":[0.0,0.0,0.0,1.0]},{"destroyable":false,"alone":false,"emissionUpEnabled":true,"emissionRightEnabled":false,"emissionLeftEnabled":false,"emissionDownEnabled":true,"position":[-86.3999938964844,-105.599868774414,0.0],"rotation":[0.0,0.0,0.0,1.0]},{"destroyable":false,"alone":false,"emissionUpEnabled":true,"emissionRightEnabled":false,"emissionLeftEnabled":false,"emissionDownEnabled":true,"position":[-83.1999969482422,-105.599868774414,0.0],"rotation":[0.0,0.0,0.0,1.0]},{"destroyable":false,"alone":false,"emissionUpEnabled":true,"emissionRightEnabled":false,"emissionLeftEnabled":true,"emissionDownEnabled":false,"position":[-112.0,-83.1998901367188,0.0],"rotation":[0.0,0.0,0.0,1.0]},{"destroyable":false,"alone":false,"emissionUpEnabled":true,"emissionRightEnabled":false,"emissionLeftEnabled":false,"emissionDownEnabled":true,"position":[-108.800003051758,-83.1998901367188,0.0],"rotation":[0.0,0.0,0.0,1.0]},{"destroyable":false,"alone":false,"emissionUpEnabled":true,"emissionRightEnabled":false,"emissionLeftEnabled":false,"emissionDownEnabled":true,"position":[-105.599998474121,-83.1998901367188,0.0],"rotation":[0.0,0.0,0.0,1.0]},{"destroyable":false,"alone":false,"emissionUpEnabled":true,"emissionRightEnabled":false,"emissionLeftEnabled":false,"emissionDownEnabled":true,"position":[-102.400001525879,-83.1998901367188,0.0],"rotation":[0.0,0.0,0.0,1.0]},{"destroyable":false,"alone":false,"emissionUpEnabled":true,"emissionRightEnabled":false,"emissionLeftEnabled":false,"emissionDownEnabled":true,"position":[-99.1999969482422,-83.1998901367188,0.0],"rotation":[0.0,0.0,0.0,1.0]},{"destroyable":false,"alone":false,"emissionUpEnabled":true,"emissionRightEnabled":false,"emissionLeftEnabled":false,"emissionDownEnabled":true,"position":[-96.0,-83.1998901367188,0.0],"rotation":[0.0,0.0,0.0,1.0]},{"destroyable":false,"alone":false,"emissionUpEnabled":true,"emissionRightEnabled":false,"emissionLeftEnabled":false,"emissionDownEnabled":true,"position":[-92.7999954223633,-83.1998901367188,0.0],"rotation":[0.0,0.0,0.0,1.0]},{"destroyable":false,"alone":false,"emissionUpEnabled":true,"emissionRightEnabled":false,"emissionLeftEnabled":false,"emissionDownEnabled":true,"position":[-89.5999984741211,-83.1998901367188,0.0],"rotation":[0.0,0.0,0.0,1.0]},{"destroyable":false,"alone":false,"emissionUpEnabled":true,"emissionRightEnabled":false,"emissionLeftEnabled":false,"emissionDownEnabled":true,"position":[-86.3999938964844,-83.1998901367188,0.0],"rotation":[0.0,0.0,0.0,1.0]},{"destroyable":false,"alone":false,"emissionUpEnabled":true,"emissionRightEnabled":false,"emissionLeftEnabled":false,"emissionDownEnabled":true,"position":[-83.1999969482422,-83.1998901367188,0.0],"rotation":[0.0,0.0,0.0,1.0]},{"destroyable":false,"alone":false,"emissionUpEnabled":true,"emissionRightEnabled":false,"emissionLeftEnabled":false,"emissionDownEnabled":true,"position":[-79.9999923706055,-105.599868774414,0.0],"rotation":[0.0,0.0,0.0,1.0]},{"destroyable":false,"alone":false,"emissionUpEnabled":true,"emissionRightEnabled":false,"emissionLeftEnabled":false,"emissionDownEnabled":true,"position":[-76.7999954223633,-105.599868774414,0.0],"rotation":[0.0,0.0,0.0,1.0]},{"destroyable":false,"alone":false,"emissionUpEnabled":true,"emissionRightEnabled":false,"emissionLeftEnabled":false,"emissionDownEnabled":true,"position":[-73.5999908447266,-105.599868774414,0.0],"rotation":[0.0,0.0,0.0,1.0]},{"destroyable":false,"alone":false,"emissionUpEnabled":true,"emissionRightEnabled":false,"emissionLeftEnabled":false,"emissionDownEnabled":true,"position":[-70.3999938964844,-105.599868774414,0.0],"rotation":[0.0,0.0,0.0,1.0]},{"destroyable":false,"alone":false,"emissionUpEnabled":true,"emissionRightEnabled":false,"emissionLeftEnabled":false,"emissionDownEnabled":true,"position":[-67.1999893188477,-105.599868774414,0.0],"rotation":[0.0,0.0,0.0,1.0]},{"destroyable":false,"alone":false,"emissionUpEnabled":true,"emissionRightEnabled":false,"emissionLeftEnabled":false,"emissionDownEnabled":true,"position":[-63.9999923706055,-105.599868774414,0.0],"rotation":[0.0,0.0,0.0,1.0]},{"destroyable":false,"alone":false,"emissionUpEnabled":true,"emissionRightEnabled":false,"emissionLeftEnabled":false,"emissionDownEnabled":true,"position":[-60.799991607666,-105.599868774414,0.0],"rotation":[0.0,0.0,0.0,1.0]},{"destroyable":false,"alone":false,"emissionUpEnabled":true,"emissionRightEnabled":false,"emissionLeftEnabled":false,"emissionDownEnabled":true,"position":[-57.5999908447266,-105.599868774414,0.0],"rotation":[0.0,0.0,0.0,1.0]},{"destroyable":false,"alone":false,"emissionUpEnabled":true,"emissionRightEnabled":false,"emissionLeftEnabled":false,"emissionDownEnabled":true,"position":[-79.9999923706055,-83.1998901367188,0.0],"rotation":[0.0,0.0,0.0,1.0]},{"destroyable":false,"alone":false,"emissionUpEnabled":true,"emissionRightEnabled":false,"emissionLeftEnabled":false,"emissionDownEnabled":false,"position":[-28.8000144958496,-35.1999359130859,0.0],"rotation":[0.0,0.0,0.0,1.0]},{"destroyable":false,"alone":false,"emissionUpEnabled":true,"emissionRightEnabled":false,"emissionLeftEnabled":false,"emissionDownEnabled":true,"position":[-25.6000175476074,-35.1999359130859,0.0],"rotation":[0.0,0.0,0.0,1.0]},{"destroyable":false,"alone":false,"emissionUpEnabled":true,"emissionRightEnabled":false,"emissionLeftEnabled":false,"emissionDownEnabled":true,"position":[-22.4000205993652,-35.1999359130859,0.0],"rotation":[0.0,0.0,0.0,1.0]},{"destroyable":false,"alone":false,"emissionUpEnabled":true,"emissionRightEnabled":false,"emissionLeftEnabled":false,"emissionDownEnabled":true,"position":[-19.200023651123,-35.1999359130859,0.0],"rotation":[0.0,0.0,0.0,1.0]},{"destroyable":false,"alone":false,"emissionUpEnabled":true,"emissionRightEnabled":false,"emissionLeftEnabled":false,"emissionDownEnabled":true,"position":[-16.0000267028809,-35.1999359130859,0.0],"rotation":[0.0,0.0,0.0,1.0]},{"destroyable":false,"alone":false,"emissionUpEnabled":true,"emissionRightEnabled":false,"emissionLeftEnabled":false,"emissionDownEnabled":true,"position":[-12.8000288009644,-35.1999359130859,0.0],"rotation":[0.0,0.0,0.0,1.0]},{"destroyable":false,"alone":false,"emissionUpEnabled":true,"emissionRightEnabled":false,"emissionLeftEnabled":false,"emissionDownEnabled":true,"position":[-9.60003185272217,-35.1999359130859,0.0],"rotation":[0.0,0.0,0.0,1.0]},{"destroyable":false,"alone":false,"emissionUpEnabled":true,"emissionRightEnabled":false,"emissionLeftEnabled":false,"emissionDownEnabled":true,"position":[-6.40003490447998,-35.1999359130859,0.0],"rotation":[0.0,0.0,0.0,1.0]},{"destroyable":false,"alone":false,"emissionUpEnabled":false,"emissionRightEnabled":true,"emissionLeftEnabled":false,"emissionDownEnabled":true,"position":[-6.40003490447998,-15.9999465942383,0.0],"rotation":[0.0,0.0,0.0,1.0]},{"destroyable":false,"alone":false,"emissionUpEnabled":false,"emissionRightEnabled":true,"emissionLeftEnabled":true,"emissionDownEnabled":false,"position":[-6.40003490447998,-12.7999496459961,0.0],"rotation":[0.0,0.0,0.0,1.0]},{"destroyable":false,"alone":false,"emissionUpEnabled":false,"emissionRightEnabled":true,"emissionLeftEnabled":true,"emissionDownEnabled":false,"position":[-6.40003490447998,-9.59995269775391,0.0],"rotation":[0.0,0.0,0.0,1.0]},{"destroyable":false,"alone":false,"emissionUpEnabled":false,"emissionRightEnabled":true,"emissionLeftEnabled":true,"emissionDownEnabled":false,"position":[-6.40003490447998,-6.39995574951172,0.0],"rotation":[0.0,0.0,0.0,1.0]},{"destroyable":false,"alone":false,"emissionUpEnabled":false,"emissionRightEnabled":true,"emissionLeftEnabled":true,"emissionDownEnabled":false,"position":[-6.40003490447998,-3.19995880126953,0.0],"rotation":[0.0,0.0,0.0,1.0]},{"destroyable":false,"alone":false,"emissionUpEnabled":false,"emissionRightEnabled":true,"emissionLeftEnabled":true,"emissionDownEnabled":false,"position":[-6.40003490447998,3.814697265625E-05,0.0],"rotation":[0.0,0.0,0.0,1.0]},{"destroyable":false,"alone":false,"emissionUpEnabled":false,"emissionRightEnabled":true,"emissionLeftEnabled":true,"emissionDownEnabled":false,"position":[-6.40003490447998,3.20003509521484,0.0],"rotation":[0.0,0.0,0.0,1.0]},{"destroyable":false,"alone":false,"emissionUpEnabled":false,"emissionRightEnabled":true,"emissionLeftEnabled":true,"emissionDownEnabled":false,"position":[-6.40003490447998,6.40003204345703,0.0],"rotation":[0.0,0.0,0.0,1.0]},{"destroyable":false,"alone":false,"emissionUpEnabled":false,"emissionRightEnabled":true,"emissionLeftEnabled":true,"emissionDownEnabled":false,"position":[-6.40003490447998,9.60002899169922,0.0],"rotation":[0.0,0.0,0.0,1.0]},{"destroyable":false,"alone":false,"emissionUpEnabled":false,"emissionRightEnabled":true,"emissionLeftEnabled":true,"emissionDownEnabled":false,"position":[-6.40003490447998,12.8000259399414,0.0],"rotation":[0.0,0.0,0.0,1.0]},{"destroyable":false,"alone":false,"emissionUpEnabled":false,"emissionRightEnabled":true,"emissionLeftEnabled":true,"emissionDownEnabled":false,"position":[-6.40003490447998,16.0000228881836,0.0],"rotation":[0.0,0.0,0.0,1.0]},{"destroyable":false,"alone":false,"emissionUpEnabled":false,"emissionRightEnabled":true,"emissionLeftEnabled":true,"emissionDownEnabled":false,"position":[-6.40003490447998,19.2000198364258,0.0],"rotation":[0.0,0.0,0.0,1.0]},{"destroyable":false,"alone":false,"emissionUpEnabled":false,"emissionRightEnabled":true,"emissionLeftEnabled":true,"emissionDownEnabled":false,"position":[-6.40003490447998,22.400016784668,0.0],"rotation":[0.0,0.0,0.0,1.0]},{"destroyable":false,"alone":false,"emissionUpEnabled":false,"emissionRightEnabled":true,"emissionLeftEnabled":true,"emissionDownEnabled":false,"position":[-6.40003490447998,25.6000137329102,0.0],"rotation":[0.0,0.0,0.0,1.0]},{"destroyable":false,"alone":false,"emissionUpEnabled":false,"emissionRightEnabled":true,"emissionLeftEnabled":true,"emissionDownEnabled":false,"position":[-6.40003490447998,28.8000106811523,0.0],"rotation":[0.0,0.0,0.0,1.0]},{"destroyable":false,"alone":false,"emissionUpEnabled":false,"emissionRightEnabled":true,"emissionLeftEnabled":true,"emissionDownEnabled":false,"position":[-6.40003490447998,32.0000076293945,0.0],"rotation":[0.0,0.0,0.0,1.0]},{"destroyable":false,"alone":false,"emissionUpEnabled":false,"emissionRightEnabled":true,"emissionLeftEnabled":true,"emissionDownEnabled":false,"position":[-6.40003490447998,35.2000045776367,0.0],"rotation":[0.0,0.0,0.0,1.0]},{"destroyable":false,"alone":false,"emissionUpEnabled":false,"emissionRightEnabled":true,"emissionLeftEnabled":true,"emissionDownEnabled":false,"position":[-6.40003490447998,38.4000015258789,0.0],"rotation":[0.0,0.0,0.0,1.0]},{"destroyable":false,"alone":false,"emissionUpEnabled":false,"emissionRightEnabled":true,"emissionLeftEnabled":true,"emissionDownEnabled":false,"position":[-6.40003490447998,41.5999984741211,0.0],"rotation":[0.0,0.0,0.0,1.0]},{"destroyable":false,"alone":false,"emissionUpEnabled":false,"emissionRightEnabled":true,"emissionLeftEnabled":true,"emissionDownEnabled":false,"position":[-6.40003490447998,44.7999954223633,0.0],"rotation":[0.0,0.0,0.0,1.0]},{"destroyable":false,"alone":false,"emissionUpEnabled":false,"emissionRightEnabled":true,"emissionLeftEnabled":false,"emissionDownEnabled":true,"position":[-28.8000144958496,-105.599868774414,0.0],"rotation":[0.0,0.0,0.0,1.0]},{"destroyable":false,"alone":false,"emissionUpEnabled":false,"emissionRightEnabled":true,"emissionLeftEnabled":true,"emissionDownEnabled":false,"position":[-28.8000144958496,-102.399871826172,0.0],"rotation":[0.0,0.0,0.0,1.0]},{"destroyable":false,"alone":false,"emissionUpEnabled":false,"emissionRightEnabled":true,"emissionLeftEnabled":true,"emissionDownEnabled":false,"position":[-28.8000144958496,-99.1998748779297,0.0],"rotation":[0.0,0.0,0.0,1.0]},{"destroyable":false,"alone":false,"emissionUpEnabled":false,"emissionRightEnabled":true,"emissionLeftEnabled":true,"emissionDownEnabled":false,"position":[-28.8000144958496,-95.9998779296875,0.0],"rotation":[0.0,0.0,0.0,1.0]},{"destroyable":false,"alone":false,"emissionUpEnabled":false,"emissionRightEnabled":true,"emissionLeftEnabled":true,"emissionDownEnabled":false,"position":[-28.8000144958496,-92.7998809814453,0.0],"rotation":[0.0,0.0,0.0,1.0]},{"destroyable":false,"alone":false,"emissionUpEnabled":false,"emissionRightEnabled":true,"emissionLeftEnabled":true,"emissionDownEnabled":false,"position":[-28.8000144958496,-89.5998840332031,0.0],"rotation":[0.0,0.0,0.0,1.0]},{"destroyable":false,"alone":false,"emissionUpEnabled":false,"emissionRightEnabled":true,"emissionLeftEnabled":true,"emissionDownEnabled":false,"position":[-28.8000144958496,-86.3998870849609,0.0],"rotation":[0.0,0.0,0.0,1.0]},{"destroyable":false,"alone":false,"emissionUpEnabled":false,"emissionRightEnabled":true,"emissionLeftEnabled":true,"emissionDownEnabled":false,"position":[-28.8000144958496,-83.1998901367188,0.0],"rotation":[0.0,0.0,0.0,1.0]},{"destroyable":false,"alone":false,"emissionUpEnabled":false,"emissionRightEnabled":true,"emissionLeftEnabled":true,"emissionDownEnabled":false,"position":[-28.8000144958496,-79.9998931884766,0.0],"rotation":[0.0,0.0,0.0,1.0]},{"destroyable":false,"alone":false,"emissionUpEnabled":false,"emissionRightEnabled":true,"emissionLeftEnabled":true,"emissionDownEnabled":false,"position":[-28.8000144958496,-73.5998992919922,0.0],"rotation":[0.0,0.0,0.0,1.0]},{"destroyable":false,"alone":false,"emissionUpEnabled":false,"emissionRightEnabled":true,"emissionLeftEnabled":true,"emissionDownEnabled":false,"position":[-28.8000144958496,-70.39990234375,0.0],"rotation":[0.0,0.0,0.0,1.0]},{"destroyable":false,"alone":false,"emissionUpEnabled":false,"emissionRightEnabled":true,"emissionLeftEnabled":true,"emissionDownEnabled":false,"position":[-28.8000144958496,-67.1999053955078,0.0],"rotation":[0.0,0.0,0.0,1.0]},{"destroyable":false,"alone":false,"emissionUpEnabled":false,"emissionRightEnabled":true,"emissionLeftEnabled":true,"emissionDownEnabled":false,"position":[-28.8000144958496,-63.9999084472656,0.0],"rotation":[0.0,0.0,0.0,1.0]},{"destroyable":false,"alone":false,"emissionUpEnabled":false,"emissionRightEnabled":true,"emissionLeftEnabled":true,"emissionDownEnabled":false,"position":[-28.8000144958496,-60.7999114990234,0.0],"rotation":[0.0,0.0,0.0,1.0]},{"destroyable":false,"alone":false,"emissionUpEnabled":false,"emissionRightEnabled":true,"emissionLeftEnabled":true,"emissionDownEnabled":false,"position":[-28.8000144958496,-57.5999145507813,0.0],"rotation":[0.0,0.0,0.0,1.0]},{"destroyable":false,"alone":false,"emissionUpEnabled":false,"emissionRightEnabled":true,"emissionLeftEnabled":true,"emissionDownEnabled":false,"position":[-28.8000144958496,-54.3999176025391,0.0],"rotation":[0.0,0.0,0.0,1.0]},{"destroyable":false,"alone":false,"emissionUpEnabled":false,"emissionRightEnabled":true,"emissionLeftEnabled":true,"emissionDownEnabled":false,"position":[-28.8000144958496,-51.1999206542969,0.0],"rotation":[0.0,0.0,0.0,1.0]},{"destroyable":false,"alone":false,"emissionUpEnabled":false,"emissionRightEnabled":true,"emissionLeftEnabled":true,"emissionDownEnabled":false,"position":[-28.8000144958496,-47.9999237060547,0.0],"rotation":[0.0,0.0,0.0,1.0]},{"destroyable":false,"alone":false,"emissionUpEnabled":false,"emissionRightEnabled":true,"emissionLeftEnabled":true,"emissionDownEnabled":false,"position":[-28.8000144958496,-44.7999267578125,0.0],"rotation":[0.0,0.0,0.0,1.0]},{"destroyable":false,"alone":false,"emissionUpEnabled":false,"emissionRightEnabled":true,"emissionLeftEnabled":true,"emissionDownEnabled":false,"position":[-28.8000144958496,-41.5999298095703,0.0],"rotation":[0.0,0.0,0.0,1.0]},{"destroyable":false,"alone":false,"emissionUpEnabled":false,"emissionRightEnabled":true,"emissionLeftEnabled":true,"emissionDownEnabled":false,"position":[-28.8000144958496,-38.3999328613281,0.0],"rotation":[0.0,0.0,0.0,1.0]},{"destroyable":false,"alone":false,"emissionUpEnabled":false,"emissionRightEnabled":true,"emissionLeftEnabled":true,"emissionDownEnabled":false,"position":[-28.8000144958496,-76.7998962402344,0.0],"rotation":[0.0,0.0,0.0,1.0]},{"destroyable":false,"alone":false,"emissionUpEnabled":true,"emissionRightEnabled":false,"emissionLeftEnabled":false,"emissionDownEnabled":true,"position":[-32.0000114440918,-105.599868774414,0.0],"rotation":[0.0,0.0,0.0,1.0]},{"destroyable":false,"alone":false,"emissionUpEnabled":true,"emissionRightEnabled":false,"emissionLeftEnabled":false,"emissionDownEnabled":true,"position":[-35.200008392334,-105.599868774414,0.0],"rotation":[0.0,0.0,0.0,1.0]},{"destroyable":false,"alone":false,"emissionUpEnabled":true,"emissionRightEnabled":false,"emissionLeftEnabled":false,"emissionDownEnabled":true,"position":[-38.4000053405762,-105.599868774414,0.0],"rotation":[0.0,0.0,0.0,1.0]},{"destroyable":false,"alone":false,"emissionUpEnabled":true,"emissionRightEnabled":false,"emissionLeftEnabled":false,"emissionDownEnabled":true,"position":[-41.6000022888184,-105.599868774414,0.0],"rotation":[0.0,0.0,0.0,1.0]},{"destroyable":false,"alone":false,"emissionUpEnabled":true,"emissionRightEnabled":false,"emissionLeftEnabled":false,"emissionDownEnabled":true,"position":[-44.7999992370605,-105.599868774414,0.0],"rotation":[0.0,0.0,0.0,1.0]},{"destroyable":false,"alone":false,"emissionUpEnabled":true,"emissionRightEnabled":false,"emissionLeftEnabled":false,"emissionDownEnabled":true,"position":[-47.9999961853027,-105.599868774414,0.0],"rotation":[0.0,0.0,0.0,1.0]},{"destroyable":false,"alone":false,"emissionUpEnabled":true,"emissionRightEnabled":false,"emissionLeftEnabled":false,"emissionDownEnabled":true,"position":[-51.1999931335449,-105.599868774414,0.0],"rotation":[0.0,0.0,0.0,1.0]},{"destroyable":false,"alone":false,"emissionUpEnabled":true,"emissionRightEnabled":false,"emissionLeftEnabled":false,"emissionDownEnabled":true,"position":[-54.3999900817871,-105.599868774414,0.0],"rotation":[0.0,0.0,0.0,1.0]},{"destroyable":false,"alone":false,"emissionUpEnabled":true,"emissionRightEnabled":false,"emissionLeftEnabled":false,"emissionDownEnabled":true,"position":[-76.7999954223633,-83.1998901367188,0.0],"rotation":[0.0,0.0,0.0,1.0]},{"destroyable":false,"alone":false,"emissionUpEnabled":true,"emissionRightEnabled":false,"emissionLeftEnabled":false,"emissionDownEnabled":true,"position":[-73.5999908447266,-83.1998901367188,0.0],"rotation":[0.0,0.0,0.0,1.0]},{"destroyable":false,"alone":false,"emissionUpEnabled":true,"emissionRightEnabled":false,"emissionLeftEnabled":false,"emissionDownEnabled":true,"position":[-70.3999938964844,-83.1998901367188,0.0],"rotation":[0.0,0.0,0.0,1.0]},{"destroyable":false,"alone":false,"emissionUpEnabled":true,"emissionRightEnabled":false,"emissionLeftEnabled":false,"emissionDownEnabled":true,"position":[-67.1999893188477,-83.1998901367188,0.0],"rotation":[0.0,0.0,0.0,1.0]},{"destroyable":false,"alone":false,"emissionUpEnabled":true,"emissionRightEnabled":false,"emissionLeftEnabled":false,"emissionDownEnabled":true,"position":[-63.9999923706055,-83.1998901367188,0.0],"rotation":[0.0,0.0,0.0,1.0]},{"destroyable":false,"alone":false,"emissionUpEnabled":true,"emissionRightEnabled":false,"emissionLeftEnabled":false,"emissionDownEnabled":true,"position":[-60.799991607666,-83.1998901367188,0.0],"rotation":[0.0,0.0,0.0,1.0]},{"destroyable":false,"alone":false,"emissionUpEnabled":true,"emissionRightEnabled":false,"emissionLeftEnabled":false,"emissionDownEnabled":true,"position":[-57.5999908447266,-83.1998901367188,0.0],"rotation":[0.0,0.0,0.0,1.0]},{"destroyable":false,"alone":false,"emissionUpEnabled":true,"emissionRightEnabled":false,"emissionLeftEnabled":false,"emissionDownEnabled":true,"position":[-54.3999900817871,-83.1998901367188,0.0],"rotation":[0.0,0.0,0.0,1.0]},{"destroyable":false,"alone":false,"emissionUpEnabled":false,"emissionRightEnabled":true,"emissionLeftEnabled":false,"emissionDownEnabled":true,"position":[-51.1999931335449,-83.1998901367188,0.0],"rotation":[0.0,0.0,0.0,1.0]},{"destroyable":false,"alone":false,"emissionUpEnabled":false,"emissionRightEnabled":true,"emissionLeftEnabled":true,"emissionDownEnabled":false,"position":[-51.1999931335449,-79.9998931884766,0.0],"rotation":[0.0,0.0,0.0,1.0]},{"destroyable":false,"alone":false,"emissionUpEnabled":false,"emissionRightEnabled":true,"emissionLeftEnabled":true,"emissionDownEnabled":false,"position":[-51.1999931335449,-76.7998962402344,0.0],"rotation":[0.0,0.0,0.0,1.0]},{"destroyable":false,"alone":false,"emissionUpEnabled":false,"emissionRightEnabled":true,"emissionLeftEnabled":true,"emissionDownEnabled":false,"position":[-51.1999931335449,-73.5998992919922,0.0],"rotation":[0.0,0.0,0.0,1.0]},{"destroyable":false,"alone":false,"emissionUpEnabled":false,"emissionRightEnabled":true,"emissionLeftEnabled":true,"emissionDownEnabled":false,"position":[-51.1999931335449,-70.39990234375,0.0],"rotation":[0.0,0.0,0.0,1.0]},{"destroyable":false,"alone":false,"emissionUpEnabled":false,"emissionRightEnabled":true,"emissionLeftEnabled":true,"emissionDownEnabled":false,"position":[-51.1999931335449,-67.1999053955078,0.0],"rotation":[0.0,0.0,0.0,1.0]},{"destroyable":false,"alone":false,"emissionUpEnabled":false,"emissionRightEnabled":true,"emissionLeftEnabled":true,"emissionDownEnabled":false,"position":[-51.1999931335449,-63.9999084472656,0.0],"rotation":[0.0,0.0,0.0,1.0]},{"destroyable":false,"alone":false,"emissionUpEnabled":false,"emissionRightEnabled":true,"emissionLeftEnabled":true,"emissionDownEnabled":false,"position":[-51.1999931335449,-60.7999114990234,0.0],"rotation":[0.0,0.0,0.0,1.0]},{"destroyable":false,"alone":false,"emissionUpEnabled":false,"emissionRightEnabled":true,"emissionLeftEnabled":true,"emissionDownEnabled":false,"position":[-51.1999931335449,-57.5999145507813,0.0],"rotation":[0.0,0.0,0.0,1.0]},{"destroyable":false,"alone":false,"emissionUpEnabled":false,"emissionRightEnabled":true,"emissionLeftEnabled":true,"emissionDownEnabled":false,"position":[-51.1999931335449,-54.3999176025391,0.0],"rotation":[0.0,0.0,0.0,1.0]},{"destroyable":false,"alone":false,"emissionUpEnabled":false,"emissionRightEnabled":true,"emissionLeftEnabled":true,"emissionDownEnabled":false,"position":[-51.1999931335449,-51.1999206542969,0.0],"rotation":[0.0,0.0,0.0,1.0]},{"destroyable":false,"alone":false,"emissionUpEnabled":false,"emissionRightEnabled":true,"emissionLeftEnabled":true,"emissionDownEnabled":false,"position":[-51.1999931335449,-47.9999237060547,0.0],"rotation":[0.0,0.0,0.0,1.0]},{"destroyable":false,"alone":false,"emissionUpEnabled":false,"emissionRightEnabled":true,"emissionLeftEnabled":true,"emissionDownEnabled":false,"position":[-51.1999931335449,-44.7999267578125,0.0],"rotation":[0.0,0.0,0.0,1.0]},{"destroyable":false,"alone":false,"emissionUpEnabled":false,"emissionRightEnabled":true,"emissionLeftEnabled":true,"emissionDownEnabled":false,"position":[-51.1999931335449,-41.5999298095703,0.0],"rotation":[0.0,0.0,0.0,1.0]},{"destroyable":false,"alone":false,"emissionUpEnabled":false,"emissionRightEnabled":true,"emissionLeftEnabled":true,"emissionDownEnabled":false,"position":[-51.1999931335449,-38.3999328613281,0.0],"rotation":[0.0,0.0,0.0,1.0]},{"destroyable":false,"alone":false,"emissionUpEnabled":false,"emissionRightEnabled":false,"emissionLeftEnabled":true,"emissionDownEnabled":false,"position":[-51.1999931335449,-35.1999359130859,0.0],"rotation":[0.0,0.0,0.0,1.0]},{"destroyable":false,"alone":false,"emissionUpEnabled":true,"emissionRightEnabled":false,"emissionLeftEnabled":false,"emissionDownEnabled":true,"position":[-89.5999984741211,-105.599868774414,0.0],"rotation":[0.0,0.0,0.0,1.0]},{"destroyable":false,"alone":false,"emissionUpEnabled":true,"emissionRightEnabled":false,"emissionLeftEnabled":false,"emissionDownEnabled":true,"position":[-92.7999954223633,-105.599868774414,0.0],"rotation":[0.0,0.0,0.0,1.0]},{"destroyable":false,"alone":false,"emissionUpEnabled":false,"emissionRightEnabled":true,"emissionLeftEnabled":true,"emissionDownEnabled":false,"position":[-51.1999931335449,-31.9999389648438,0.0],"rotation":[0.0,0.0,0.0,1.0]},{"destroyable":false,"alone":false,"emissionUpEnabled":false,"emissionRightEnabled":true,"emissionLeftEnabled":true,"emissionDownEnabled":false,"position":[-51.1999931335449,-28.7999420166016,0.0],"rotation":[0.0,0.0,0.0,1.0]},{"destroyable":false,"alone":false,"emissionUpEnabled":false,"emissionRightEnabled":true,"emissionLeftEnabled":true,"emissionDownEnabled":false,"position":[-51.1999931335449,-25.5999450683594,0.0],"rotation":[0.0,0.0,0.0,1.0]},{"destroyable":false,"alone":false,"emissionUpEnabled":false,"emissionRightEnabled":true,"emissionLeftEnabled":true,"emissionDownEnabled":false,"position":[-51.1999931335449,-22.3999481201172,0.0],"rotation":[0.0,0.0,0.0,1.0]},{"destroyable":false,"alone":false,"emissionUpEnabled":false,"emissionRightEnabled":true,"emissionLeftEnabled":true,"emissionDownEnabled":false,"position":[-51.1999931335449,-19.199951171875,0.0],"rotation":[0.0,0.0,0.0,1.0]},{"destroyable":false,"alone":false,"emissionUpEnabled":true,"emissionRightEnabled":false,"emissionLeftEnabled":true,"emissionDownEnabled":false,"position":[-51.1999931335449,-15.9999465942383,0.0],"rotation":[0.0,0.0,0.0,1.0]},{"destroyable":false,"alone":false,"emissionUpEnabled":true,"emissionRightEnabled":false,"emissionLeftEnabled":false,"emissionDownEnabled":true,"position":[-47.9999961853027,-15.9999465942383,0.0],"rotation":[0.0,0.0,0.0,1.0]},{"destroyable":false,"alone":false,"emissionUpEnabled":true,"emissionRightEnabled":false,"emissionLeftEnabled":false,"emissionDownEnabled":true,"position":[-44.7999992370605,-15.9999465942383,0.0],"rotation":[0.0,0.0,0.0,1.0]},{"destroyable":false,"alone":false,"emissionUpEnabled":true,"emissionRightEnabled":false,"emissionLeftEnabled":false,"emissionDownEnabled":true,"position":[-41.6000022888184,-15.9999465942383,0.0],"rotation":[0.0,0.0,0.0,1.0]},{"destroyable":false,"alone":false,"emissionUpEnabled":true,"emissionRightEnabled":false,"emissionLeftEnabled":false,"emissionDownEnabled":true,"position":[-38.4000053405762,-15.9999465942383,0.0],"rotation":[0.0,0.0,0.0,1.0]},{"destroyable":false,"alone":false,"emissionUpEnabled":true,"emissionRightEnabled":false,"emissionLeftEnabled":false,"emissionDownEnabled":true,"position":[-35.200008392334,-15.9999465942383,0.0],"rotation":[0.0,0.0,0.0,1.0]},{"destroyable":false,"alone":false,"emissionUpEnabled":true,"emissionRightEnabled":false,"emissionLeftEnabled":false,"emissionDownEnabled":true,"position":[-3.20003819465637,-35.1999359130859,0.0],"rotation":[0.0,0.0,0.0,1.0]},{"destroyable":false,"alone":false,"emissionUpEnabled":true,"emissionRightEnabled":false,"emissionLeftEnabled":false,"emissionDownEnabled":true,"position":[-4.12464141845703E-05,-35.1999359130859,0.0],"rotation":[0.0,0.0,0.0,1.0]},{"destroyable":false,"alone":false,"emissionUpEnabled":true,"emissionRightEnabled":false,"emissionLeftEnabled":false,"emissionDownEnabled":true,"position":[3.199955701828,-35.1999359130859,0.0],"rotation":[0.0,0.0,0.0,1.0]},{"destroyable":false,"alone":false,"emissionUpEnabled":true,"emissionRightEnabled":false,"emissionLeftEnabled":false,"emissionDownEnabled":true,"position":[-32.0000114440918,-15.9999465942383,0.0],"rotation":[0.0,0.0,0.0,1.0]},{"destroyable":false,"alone":false,"emissionUpEnabled":true,"emissionRightEnabled":false,"emissionLeftEnabled":false,"emissionDownEnabled":true,"position":[-28.8000144958496,-15.9999465942383,0.0],"rotation":[0.0,0.0,0.0,1.0]},{"destroyable":false,"alone":false,"emissionUpEnabled":true,"emissionRightEnabled":false,"emissionLeftEnabled":false,"emissionDownEnabled":true,"position":[-25.6000175476074,-15.9999465942383,0.0],"rotation":[0.0,0.0,0.0,1.0]},{"destroyable":false,"alone":false,"emissionUpEnabled":true,"emissionRightEnabled":false,"emissionLeftEnabled":false,"emissionDownEnabled":true,"position":[-22.4000205993652,-15.9999465942383,0.0],"rotation":[0.0,0.0,0.0,1.0]},{"destroyable":false,"alone":false,"emissionUpEnabled":true,"emissionRightEnabled":false,"emissionLeftEnabled":false,"emissionDownEnabled":true,"position":[-19.200023651123,-15.9999465942383,0.0],"rotation":[0.0,0.0,0.0,1.0]},{"destroyable":false,"alone":false,"emissionUpEnabled":true,"emissionRightEnabled":false,"emissionLeftEnabled":false,"emissionDownEnabled":true,"position":[-16.0000267028809,-15.9999465942383,0.0],"rotation":[0.0,0.0,0.0,1.0]},{"destroyable":false,"alone":false,"emissionUpEnabled":true,"emissionRightEnabled":false,"emissionLeftEnabled":false,"emissionDownEnabled":true,"position":[-12.8000288009644,-15.9999465942383,0.0],"rotation":[0.0,0.0,0.0,1.0]},{"destroyable":false,"alone":false,"emissionUpEnabled":true,"emissionRightEnabled":false,"emissionLeftEnabled":false,"emissionDownEnabled":true,"position":[-9.60003185272217,-15.9999465942383,0.0],"rotation":[0.0,0.0,0.0,1.0]},{"destroyable":false,"alone":false,"emissionUpEnabled":true,"emissionRightEnabled":false,"emissionLeftEnabled":false,"emissionDownEnabled":true,"position":[6.39995288848877,-35.1999359130859,0.0],"rotation":[0.0,0.0,0.0,1.0]},{"destroyable":false,"alone":false,"emissionUpEnabled":true,"emissionRightEnabled":false,"emissionLeftEnabled":false,"emissionDownEnabled":true,"position":[9.59994983673096,-35.1999359130859,0.0],"rotation":[0.0,0.0,0.0,1.0]},{"destroyable":false,"alone":false,"emissionUpEnabled":true,"emissionRightEnabled":false,"emissionLeftEnabled":false,"emissionDownEnabled":true,"position":[12.7999467849731,-35.1999359130859,0.0],"rotation":[0.0,0.0,0.0,1.0]},{"destroyable":false,"alone":false,"emissionUpEnabled":true,"emissionRightEnabled":false,"emissionLeftEnabled":false,"emissionDownEnabled":true,"position":[15.9999513626099,-35.1999359130859,0.0],"rotation":[0.0,0.0,0.0,1.0]},{"destroyable":false,"alone":false,"emissionUpEnabled":false,"emissionRightEnabled":true,"emissionLeftEnabled":false,"emissionDownEnabled":true,"position":[19.1999473571777,-35.1999359130859,0.0],"rotation":[0.0,0.0,0.0,1.0]},{"destroyable":false,"alone":false,"emissionUpEnabled":false,"emissionRightEnabled":true,"emissionLeftEnabled":true,"emissionDownEnabled":false,"position":[19.1999473571777,-31.9999389648438,0.0],"rotation":[0.0,0.0,0.0,1.0]},{"destroyable":false,"alone":false,"emissionUpEnabled":false,"emissionRightEnabled":true,"emissionLeftEnabled":true,"emissionDownEnabled":false,"position":[19.1999473571777,-28.7999420166016,0.0],"rotation":[0.0,0.0,0.0,1.0]},{"destroyable":false,"alone":false,"emissionUpEnabled":false,"emissionRightEnabled":true,"emissionLeftEnabled":true,"emissionDownEnabled":false,"position":[19.1999473571777,-25.5999450683594,0.0],"rotation":[0.0,0.0,0.0,1.0]},{"destroyable":false,"alone":false,"emissionUpEnabled":false,"emissionRightEnabled":true,"emissionLeftEnabled":true,"emissionDownEnabled":false,"position":[19.1999473571777,-22.3999481201172,0.0],"rotation":[0.0,0.0,0.0,1.0]},{"destroyable":false,"alone":false,"emissionUpEnabled":false,"emissionRightEnabled":true,"emissionLeftEnabled":true,"emissionDownEnabled":false,"position":[19.1999473571777,-19.199951171875,0.0],"rotation":[0.0,0.0,0.0,1.0]},{"destroyable":false,"alone":false,"emissionUpEnabled":false,"emissionRightEnabled":true,"emissionLeftEnabled":true,"emissionDownEnabled":false,"position":[19.1999473571777,-15.9999465942383,0.0],"rotation":[0.0,0.0,0.0,1.0]},{"destroyable":false,"alone":false,"emissionUpEnabled":false,"emissionRightEnabled":true,"emissionLeftEnabled":true,"emissionDownEnabled":false,"position":[19.1999473571777,-12.7999496459961,0.0],"rotation":[0.0,0.0,0.0,1.0]},{"destroyable":false,"alone":false,"emissionUpEnabled":false,"emissionRightEnabled":true,"emissionLeftEnabled":true,"emissionDownEnabled":false,"position":[19.1999473571777,-9.59995269775391,0.0],"rotation":[0.0,0.0,0.0,1.0]},{"destroyable":false,"alone":false,"emissionUpEnabled":false,"emissionRightEnabled":true,"emissionLeftEnabled":true,"emissionDownEnabled":false,"position":[19.1999473571777,-6.39995574951172,0.0],"rotation":[0.0,0.0,0.0,1.0]},{"destroyable":false,"alone":false,"emissionUpEnabled":false,"emissionRightEnabled":true,"emissionLeftEnabled":true,"emissionDownEnabled":false,"position":[19.1999473571777,-3.19995880126953,0.0],"rotation":[0.0,0.0,0.0,1.0]},{"destroyable":false,"alone":false,"emissionUpEnabled":false,"emissionRightEnabled":true,"emissionLeftEnabled":true,"emissionDownEnabled":false,"position":[19.1999473571777,3.814697265625E-05,0.0],"rotation":[0.0,0.0,0.0,1.0]},{"destroyable":false,"alone":false,"emissionUpEnabled":false,"emissionRightEnabled":true,"emissionLeftEnabled":true,"emissionDownEnabled":false,"position":[19.1999473571777,3.20003509521484,0.0],"rotation":[0.0,0.0,0.0,1.0]},{"destroyable":false,"alone":false,"emissionUpEnabled":false,"emissionRightEnabled":true,"emissionLeftEnabled":true,"emissionDownEnabled":false,"position":[19.1999473571777,6.40003204345703,0.0],"rotation":[0.0,0.0,0.0,1.0]},{"destroyable":false,"alone":false,"emissionUpEnabled":false,"emissionRightEnabled":true,"emissionLeftEnabled":true,"emissionDownEnabled":false,"position":[19.1999473571777,9.60002899169922,0.0],"rotation":[0.0,0.0,0.0,1.0]},{"destroyable":false,"alone":false,"emissionUpEnabled":false,"emissionRightEnabled":true,"emissionLeftEnabled":true,"emissionDownEnabled":false,"position":[19.1999473571777,12.8000259399414,0.0],"rotation":[0.0,0.0,0.0,1.0]},{"destroyable":false,"alone":false,"emissionUpEnabled":false,"emissionRightEnabled":true,"emissionLeftEnabled":true,"emissionDownEnabled":false,"position":[19.1999473571777,16.0000228881836,0.0],"rotation":[0.0,0.0,0.0,1.0]},{"destroyable":false,"alone":false,"emissionUpEnabled":false,"emissionRightEnabled":true,"emissionLeftEnabled":true,"emissionDownEnabled":false,"position":[19.1999473571777,19.2000198364258,0.0],"rotation":[0.0,0.0,0.0,1.0]},{"destroyable":false,"alone":false,"emissionUpEnabled":false,"emissionRightEnabled":true,"emissionLeftEnabled":true,"emissionDownEnabled":false,"position":[19.1999473571777,22.400016784668,0.0],"rotation":[0.0,0.0,0.0,1.0]},{"destroyable":false,"alone":false,"emissionUpEnabled":false,"emissionRightEnabled":true,"emissionLeftEnabled":true,"emissionDownEnabled":false,"position":[19.1999473571777,25.6000137329102,0.0],"rotation":[0.0,0.0,0.0,1.0]},{"destroyable":false,"alone":false,"emissionUpEnabled":false,"emissionRightEnabled":true,"emissionLeftEnabled":true,"emissionDownEnabled":false,"position":[19.1999473571777,28.8000106811523,0.0],"rotation":[0.0,0.0,0.0,1.0]},{"destroyable":false,"alone":false,"emissionUpEnabled":false,"emissionRightEnabled":true,"emissionLeftEnabled":true,"emissionDownEnabled":false,"position":[19.1999473571777,32.0000076293945,0.0],"rotation":[0.0,0.0,0.0,1.0]},{"destroyable":false,"alone":false,"emissionUpEnabled":false,"emissionRightEnabled":true,"emissionLeftEnabled":true,"emissionDownEnabled":false,"position":[19.1999473571777,35.2000045776367,0.0],"rotation":[0.0,0.0,0.0,1.0]},{"destroyable":false,"alone":false,"emissionUpEnabled":false,"emissionRightEnabled":true,"emissionLeftEnabled":true,"emissionDownEnabled":false,"position":[19.1999473571777,38.4000015258789,0.0],"rotation":[0.0,0.0,0.0,1.0]},{"destroyable":false,"alone":false,"emissionUpEnabled":false,"emissionRightEnabled":true,"emissionLeftEnabled":true,"emissionDownEnabled":false,"position":[19.1999473571777,41.5999984741211,0.0],"rotation":[0.0,0.0,0.0,1.0]},{"destroyable":false,"alone":false,"emissionUpEnabled":false,"emissionRightEnabled":true,"emissionLeftEnabled":true,"emissionDownEnabled":false,"position":[19.1999473571777,44.7999954223633,0.0],"rotation":[0.0,0.0,0.0,1.0]},{"destroyable":false,"alone":false,"emissionUpEnabled":false,"emissionRightEnabled":true,"emissionLeftEnabled":true,"emissionDownEnabled":false,"position":[19.1999473571777,47.9999923706055,0.0],"rotation":[0.0,0.0,0.0,1.0]},{"destroyable":false,"alone":false,"emissionUpEnabled":false,"emissionRightEnabled":true,"emissionLeftEnabled":true,"emissionDownEnabled":false,"position":[19.1999473571777,51.1999893188477,0.0],"rotation":[0.0,0.0,0.0,1.0]},{"destroyable":false,"alone":false,"emissionUpEnabled":true,"emissionRightEnabled":false,"emissionLeftEnabled":false,"emissionDownEnabled":false,"position":[19.1999473571777,54.3999900817871,0.0],"rotation":[0.0,0.0,0.0,1.0]},{"destroyable":false,"alone":false,"emissionUpEnabled":false,"emissionRightEnabled":false,"emissionLeftEnabled":true,"emissionDownEnabled":false,"position":[-6.40003490447998,54.3999900817871,0.0],"rotation":[0.0,0.0,0.0,1.0]},{"destroyable":false,"alone":false,"emissionUpEnabled":false,"emissionRightEnabled":true,"emissionLeftEnabled":true,"emissionDownEnabled":false,"position":[-6.40003490447998,51.1999893188477,0.0],"rotation":[0.0,0.0,0.0,1.0]},{"destroyable":false,"alone":false,"emissionUpEnabled":false,"emissionRightEnabled":true,"emissionLeftEnabled":true,"emissionDownEnabled":false,"position":[-6.40003490447998,47.9999923706055,0.0],"rotation":[0.0,0.0,0.0,1.0]},{"destroyable":false,"alone":false,"emissionUpEnabled":false,"emissionRightEnabled":true,"emissionLeftEnabled":true,"emissionDownEnabled":false,"position":[-6.40003490447998,57.5999908447266,0.0],"rotation":[0.0,0.0,0.0,1.0]},{"destroyable":false,"alone":false,"emissionUpEnabled":false,"emissionRightEnabled":true,"emissionLeftEnabled":true,"emissionDownEnabled":false,"position":[-6.40003490447998,60.799991607666,0.0],"rotation":[0.0,0.0,0.0,1.0]},{"destroyable":false,"alone":false,"emissionUpEnabled":false,"emissionRightEnabled":true,"emissionLeftEnabled":true,"emissionDownEnabled":false,"position":[-6.40003490447998,63.9999923706055,0.0],"rotation":[0.0,0.0,0.0,1.0]},{"destroyable":false,"alone":false,"emissionUpEnabled":false,"emissionRightEnabled":true,"emissionLeftEnabled":true,"emissionDownEnabled":false,"position":[-6.40003490447998,67.1999969482422,0.0],"rotation":[0.0,0.0,0.0,1.0]},{"destroyable":false,"alone":false,"emissionUpEnabled":false,"emissionRightEnabled":false,"emissionLeftEnabled":true,"emissionDownEnabled":false,"position":[-6.40003490447998,70.3999938964844,0.0],"rotation":[0.0,0.0,0.0,1.0]},{"destroyable":false,"alone":false,"emissionUpEnabled":false,"emissionRightEnabled":false,"emissionLeftEnabled":true,"emissionDownEnabled":false,"position":[-6.40003490447998,73.5999908447266,0.0],"rotation":[0.0,0.0,0.0,1.0]},{"destroyable":false,"alone":false,"emissionUpEnabled":false,"emissionRightEnabled":false,"emissionLeftEnabled":true,"emissionDownEnabled":false,"position":[-6.40003490447998,76.7999954223633,0.0],"rotation":[0.0,0.0,0.0,1.0]},{"destroyable":false,"alone":false,"emissionUpEnabled":false,"emissionRightEnabled":false,"emissionLeftEnabled":true,"emissionDownEnabled":false,"position":[-6.40003490447998,80.0,0.0],"rotation":[0.0,0.0,0.0,1.0]},{"destroyable":false,"alone":false,"emissionUpEnabled":false,"emissionRightEnabled":false,"emissionLeftEnabled":true,"emissionDownEnabled":false,"position":[-6.40003490447998,83.1999969482422,0.0],"rotation":[0.0,0.0,0.0,1.0]},{"destroyable":false,"alone":false,"emissionUpEnabled":false,"emissionRightEnabled":true,"emissionLeftEnabled":false,"emissionDownEnabled":true,"position":[-3.20003819465637,70.3999938964844,0.0],"rotation":[0.0,0.0,0.0,1.0]},{"destroyable":false,"alone":false,"emissionUpEnabled":false,"emissionRightEnabled":true,"emissionLeftEnabled":false,"emissionDownEnabled":false,"position":[-3.20003819465637,73.5999908447266,0.0],"rotation":[0.0,0.0,0.0,1.0]},{"destroyable":false,"alone":false,"emissionUpEnabled":false,"emissionRightEnabled":true,"emissionLeftEnabled":false,"emissionDownEnabled":false,"position":[-3.20003819465637,76.7999954223633,0.0],"rotation":[0.0,0.0,0.0,1.0]},{"destroyable":false,"alone":false,"emissionUpEnabled":false,"emissionRightEnabled":true,"emissionLeftEnabled":false,"emissionDownEnabled":false,"position":[-3.20003819465637,80.0,0.0],"rotation":[0.0,0.0,0.0,1.0]},{"destroyable":false,"alone":false,"emissionUpEnabled":false,"emissionRightEnabled":false,"emissionLeftEnabled":false,"emissionDownEnabled":true,"position":[-4.12464141845703E-05,83.1999969482422,0.0],"rotation":[0.0,0.0,0.0,1.0]},{"destroyable":false,"alone":false,"emissionUpEnabled":false,"emissionRightEnabled":false,"emissionLeftEnabled":false,"emissionDownEnabled":false,"position":[-4.12464141845703E-05,86.3999938964844,0.0],"rotation":[0.0,0.0,0.0,1.0]},{"destroyable":false,"alone":false,"emissionUpEnabled":false,"emissionRightEnabled":false,"emissionLeftEnabled":false,"emissionDownEnabled":false,"position":[-4.12464141845703E-05,89.5999984741211,0.0],"rotation":[0.0,0.0,0.0,1.0]},{"destroyable":false,"alone":false,"emissionUpEnabled":false,"emissionRightEnabled":true,"emissionLeftEnabled":true,"emissionDownEnabled":false,"position":[-6.40003490447998,102.400001525879,0.0],"rotation":[0.0,0.0,0.0,1.0]},{"destroyable":false,"alone":false,"emissionUpEnabled":false,"emissionRightEnabled":false,"emissionLeftEnabled":true,"emissionDownEnabled":false,"position":[-6.40003490447998,99.1999969482422,0.0],"rotation":[0.0,0.0,0.0,1.0]},{"destroyable":false,"alone":false,"emissionUpEnabled":false,"emissionRightEnabled":false,"emissionLeftEnabled":true,"emissionDownEnabled":false,"position":[-6.40003490447998,96.0,0.0],"rotation":[0.0,0.0,0.0,1.0]},{"destroyable":false,"alone":false,"emissionUpEnabled":false,"emissionRightEnabled":false,"emissionLeftEnabled":true,"emissionDownEnabled":false,"position":[-6.40003490447998,92.8000030517578,0.0],"rotation":[0.0,0.0,0.0,1.0]},{"destroyable":false,"alone":false,"emissionUpEnabled":false,"emissionRightEnabled":false,"emissionLeftEnabled":true,"emissionDownEnabled":false,"position":[-6.40003490447998,89.5999984741211,0.0],"rotation":[0.0,0.0,0.0,1.0]},{"destroyable":false,"alone":false,"emissionUpEnabled":false,"emissionRightEnabled":false,"emissionLeftEnabled":true,"emissionDownEnabled":false,"position":[-6.40003490447998,86.3999938964844,0.0],"rotation":[0.0,0.0,0.0,1.0]},{"destroyable":false,"alone":false,"emissionUpEnabled":false,"emissionRightEnabled":false,"emissionLeftEnabled":false,"emissionDownEnabled":false,"position":[-3.20003819465637,89.5999984741211,0.0],"rotation":[0.0,0.0,0.0,1.0]},{"destroyable":false,"alone":false,"emissionUpEnabled":false,"emissionRightEnabled":false,"emissionLeftEnabled":false,"emissionDownEnabled":false,"position":[-3.20003819465637,86.3999938964844,0.0],"rotation":[0.0,0.0,0.0,1.0]},{"destroyable":false,"alone":false,"emissionUpEnabled":false,"emissionRightEnabled":false,"emissionLeftEnabled":false,"emissionDownEnabled":false,"position":[-3.20003819465637,83.1999969482422,0.0],"rotation":[0.0,0.0,0.0,1.0]},{"destroyable":false,"alone":false,"emissionUpEnabled":false,"emissionRightEnabled":true,"emissionLeftEnabled":false,"emissionDownEnabled":true,"position":[3.199955701828,83.1999969482422,0.0],"rotation":[0.0,0.0,0.0,1.0]},{"destroyable":false,"alone":false,"emissionUpEnabled":false,"emissionRightEnabled":true,"emissionLeftEnabled":false,"emissionDownEnabled":false,"position":[3.199955701828,86.3999938964844,0.0],"rotation":[0.0,0.0,0.0,1.0]},{"destroyable":false,"alone":false,"emissionUpEnabled":false,"emissionRightEnabled":true,"emissionLeftEnabled":false,"emissionDownEnabled":false,"position":[3.199955701828,89.5999984741211,0.0],"rotation":[0.0,0.0,0.0,1.0]},{"destroyable":false,"alone":false,"emissionUpEnabled":true,"emissionRightEnabled":false,"emissionLeftEnabled":true,"emissionDownEnabled":false,"position":[-6.40003204345703,112.0,0.0],"rotation":[0.0,0.0,0.0,1.0]},{"destroyable":false,"alone":false,"emissionUpEnabled":true,"emissionRightEnabled":false,"emissionLeftEnabled":false,"emissionDownEnabled":true,"position":[-3.20003509521484,112.0,0.0],"rotation":[0.0,0.0,0.0,1.0]},{"destroyable":false,"alone":false,"emissionUpEnabled":true,"emissionRightEnabled":false,"emissionLeftEnabled":false,"emissionDownEnabled":true,"position":[-3.814697265625E-05,112.0,0.0],"rotation":[0.0,0.0,0.0,1.0]},{"destroyable":false,"alone":false,"emissionUpEnabled":true,"emissionRightEnabled":false,"emissionLeftEnabled":false,"emissionDownEnabled":true,"position":[3.19995880126953,112.0,0.0],"rotation":[0.0,0.0,0.0,1.0]},{"destroyable":false,"alone":false,"emissionUpEnabled":true,"emissionRightEnabled":false,"emissionLeftEnabled":false,"emissionDownEnabled":true,"position":[6.39995574951172,112.0,0.0],"rotation":[0.0,0.0,0.0,1.0]},{"destroyable":false,"alone":false,"emissionUpEnabled":true,"emissionRightEnabled":false,"emissionLeftEnabled":false,"emissionDownEnabled":true,"position":[9.59995269775391,112.0,0.0],"rotation":[0.0,0.0,0.0,1.0]},{"destroyable":false,"alone":false,"emissionUpEnabled":true,"emissionRightEnabled":false,"emissionLeftEnabled":false,"emissionDownEnabled":true,"position":[12.7999496459961,112.0,0.0],"rotation":[0.0,0.0,0.0,1.0]},{"destroyable":false,"alone":false,"emissionUpEnabled":true,"emissionRightEnabled":false,"emissionLeftEnabled":false,"emissionDownEnabled":true,"position":[15.9999465942383,112.0,0.0],"rotation":[0.0,0.0,0.0,1.0]},{"destroyable":false,"alone":false,"emissionUpEnabled":false,"emissionRightEnabled":true,"emissionLeftEnabled":true,"emissionDownEnabled":false,"position":[-6.40003490447998,108.800003051758,0.0],"rotation":[0.0,0.0,0.0,1.0]},{"destroyable":false,"alone":false,"emissionUpEnabled":false,"emissionRightEnabled":true,"emissionLeftEnabled":true,"emissionDownEnabled":false,"position":[-6.40003490447998,105.599998474121,0.0],"rotation":[0.0,0.0,0.0,1.0]},{"destroyable":false,"alone":false,"emissionUpEnabled":true,"emissionRightEnabled":false,"emissionLeftEnabled":false,"emissionDownEnabled":true,"position":[19.199951171875,112.0,0.0],"rotation":[0.0,0.0,0.0,1.0]},{"destroyable":false,"alone":false,"emissionUpEnabled":true,"emissionRightEnabled":false,"emissionLeftEnabled":false,"emissionDownEnabled":true,"position":[22.3999481201172,112.0,0.0],"rotation":[0.0,0.0,0.0,1.0]},{"destroyable":false,"alone":false,"emissionUpEnabled":true,"emissionRightEnabled":false,"emissionLeftEnabled":false,"emissionDownEnabled":true,"position":[25.5999450683594,112.0,0.0],"rotation":[0.0,0.0,0.0,1.0]},{"destroyable":false,"alone":false,"emissionUpEnabled":true,"emissionRightEnabled":false,"emissionLeftEnabled":false,"emissionDownEnabled":true,"position":[28.7999420166016,112.0,0.0],"rotation":[0.0,0.0,0.0,1.0]},{"destroyable":false,"alone":false,"emissionUpEnabled":true,"emissionRightEnabled":false,"emissionLeftEnabled":false,"emissionDownEnabled":true,"position":[35.1999359130859,112.0,0.0],"rotation":[0.0,0.0,0.0,1.0]},{"destroyable":false,"alone":false,"emissionUpEnabled":true,"emissionRightEnabled":false,"emissionLeftEnabled":false,"emissionDownEnabled":true,"position":[38.3999328613281,112.0,0.0],"rotation":[0.0,0.0,0.0,1.0]},{"destroyable":false,"alone":false,"emissionUpEnabled":true,"emissionRightEnabled":false,"emissionLeftEnabled":false,"emissionDownEnabled":true,"position":[41.5999298095703,112.0,0.0],"rotation":[0.0,0.0,0.0,1.0]},{"destroyable":false,"alone":false,"emissionUpEnabled":true,"emissionRightEnabled":false,"emissionLeftEnabled":false,"emissionDownEnabled":true,"position":[44.7999267578125,112.0,0.0],"rotation":[0.0,0.0,0.0,1.0]},{"destroyable":false,"alone":false,"emissionUpEnabled":true,"emissionRightEnabled":false,"emissionLeftEnabled":false,"emissionDownEnabled":true,"position":[31.9999389648438,112.0,0.0],"rotation":[0.0,0.0,0.0,1.0]},{"destroyable":false,"alone":false,"emissionUpEnabled":true,"emissionRightEnabled":false,"emissionLeftEnabled":false,"emissionDownEnabled":true,"position":[47.9999237060547,112.0,0.0],"rotation":[0.0,0.0,0.0,1.0]},{"destroyable":false,"alone":false,"emissionUpEnabled":true,"emissionRightEnabled":true,"emissionLeftEnabled":false,"emissionDownEnabled":true,"position":[51.1999206542969,112.0,0.0],"rotation":[0.0,0.0,0.0,1.0]},{"destroyable":false,"alone":false,"emissionUpEnabled":true,"emissionRightEnabled":false,"emissionLeftEnabled":false,"emissionDownEnabled":true,"position":[22.3999443054199,54.3999900817871,0.0],"rotation":[0.0,0.0,0.0,1.0]},{"destroyable":false,"alone":false,"emissionUpEnabled":true,"emissionRightEnabled":false,"emissionLeftEnabled":false,"emissionDownEnabled":true,"position":[25.5999412536621,54.3999900817871,0.0],"rotation":[0.0,0.0,0.0,1.0]},{"destroyable":false,"alone":false,"emissionUpEnabled":true,"emissionRightEnabled":false,"emissionLeftEnabled":false,"emissionDownEnabled":true,"position":[28.7999382019043,54.3999900817871,0.0],"rotation":[0.0,0.0,0.0,1.0]},{"destroyable":false,"alone":false,"emissionUpEnabled":true,"emissionRightEnabled":false,"emissionLeftEnabled":false,"emissionDownEnabled":true,"position":[31.9999351501465,54.3999900817871,0.0],"rotation":[0.0,0.0,0.0,1.0]},{"destroyable":false,"alone":false,"emissionUpEnabled":true,"emissionRightEnabled":true,"emissionLeftEnabled":false,"emissionDownEnabled":true,"position":[35.1999320983887,54.3999900817871,0.0],"rotation":[0.0,0.0,0.0,1.0]},{"destroyable":false,"alone":false,"emissionUpEnabled":true,"emissionRightEnabled":false,"emissionLeftEnabled":true,"emissionDownEnabled":true,"position":[-32.0000114440918,-35.1999359130859,0.0],"rotation":[0.0,0.0,0.0,1.0]},{"destroyable":false,"alone":false,"emissionUpEnabled":true,"emissionRightEnabled":false,"emissionLeftEnabled":true,"emissionDownEnabled":true,"position":[15.9999513626099,54.3999900817871,0.0],"rotation":[0.0,0.0,0.0,1.0]},{"destroyable":false,"alone":false,"emissionUpEnabled":true,"emissionRightEnabled":true,"emissionLeftEnabled":false,"emissionDownEnabled":true,"position":[-3.20003819465637,54.3999900817871,0.0],"rotation":[0.0,0.0,0.0,1.0]},{"destroyable":false,"alone":false,"emissionUpEnabled":true,"emissionRightEnabled":true,"emissionLeftEnabled":false,"emissionDownEnabled":true,"position":[-47.9999961853027,-35.1999359130859,0.0],"rotation":[0.0,0.0,0.0,1.0]},{"destroyable":false,"alone":false,"emissionUpEnabled":false,"emissionRightEnabled":true,"emissionLeftEnabled":true,"emissionDownEnabled":true,"position":[92.7998809814453,60.799991607666,0.0],"rotation":[0.0,0.0,0.0,1.0]},{"destroyable":false,"alone":false,"emissionUpEnabled":false,"emissionRightEnabled":true,"emissionLeftEnabled":true,"emissionDownEnabled":false,"position":[92.7998809814453,63.9999923706055,0.0],"rotation":[0.0,0.0,0.0,1.0]},{"destroyable":false,"alone":false,"emissionUpEnabled":false,"emissionRightEnabled":true,"emissionLeftEnabled":true,"emissionDownEnabled":false,"position":[92.7998809814453,67.1999969482422,0.0],"rotation":[0.0,0.0,0.0,1.0]},{"destroyable":false,"alone":false,"emissionUpEnabled":false,"emissionRightEnabled":true,"emissionLeftEnabled":true,"emissionDownEnabled":false,"position":[92.7998809814453,70.3999938964844,0.0],"rotation":[0.0,0.0,0.0,1.0]},{"destroyable":false,"alone":false,"emissionUpEnabled":true,"emissionRightEnabled":false,"emissionLeftEnabled":true,"emissionDownEnabled":false,"position":[92.7998809814453,73.5999908447266,0.0],"rotation":[0.0,0.0,0.0,1.0]},{"destroyable":false,"alone":false,"emissionUpEnabled":true,"emissionRightEnabled":true,"emissionLeftEnabled":false,"emissionDownEnabled":true,"position":[95.9998779296875,73.5999908447266,0.0],"rotation":[0.0,0.0,0.0,1.0]},{"destroyable":false,"alone":false,"emissionUpEnabled":true,"emissionRightEnabled":true,"emissionLeftEnabled":true,"emissionDownEnabled":false,"position":[51.1999168395996,92.8000030517578,0.0],"rotation":[0.0,0.0,0.0,1.0]},{"destroyable":false,"alone":false,"emissionUpEnabled":false,"emissionRightEnabled":true,"emissionLeftEnabled":true,"emissionDownEnabled":false,"position":[51.1999168395996,89.5999984741211,0.0],"rotation":[0.0,0.0,0.0,1.0]},{"destroyable":false,"alone":false,"emissionUpEnabled":false,"emissionRightEnabled":true,"emissionLeftEnabled":true,"emissionDownEnabled":false,"position":[51.1999168395996,86.3999938964844,0.0],"rotation":[0.0,0.0,0.0,1.0]},{"destroyable":false,"alone":false,"emissionUpEnabled":false,"emissionRightEnabled":true,"emissionLeftEnabled":true,"emissionDownEnabled":false,"position":[51.1999168395996,83.1999969482422,0.0],"rotation":[0.0,0.0,0.0,1.0]},{"destroyable":false,"alone":false,"emissionUpEnabled":false,"emissionRightEnabled":true,"emissionLeftEnabled":true,"emissionDownEnabled":false,"position":[51.1999168395996,80.0,0.0],"rotation":[0.0,0.0,0.0,1.0]},{"destroyable":false,"alone":false,"emissionUpEnabled":false,"emissionRightEnabled":false,"emissionLeftEnabled":false,"emissionDownEnabled":false,"position":[3.199955701828,92.8000030517578,0.0],"rotation":[0.0,0.0,0.0,1.0]},{"destroyable":false,"alone":false,"emissionUpEnabled":false,"emissionRightEnabled":false,"emissionLeftEnabled":false,"emissionDownEnabled":false,"position":[-4.12464141845703E-05,92.8000030517578,0.0],"rotation":[0.0,0.0,0.0,1.0]},{"destroyable":false,"alone":false,"emissionUpEnabled":false,"emissionRightEnabled":false,"emissionLeftEnabled":false,"emissionDownEnabled":false,"position":[-3.20003819465637,92.8000030517578,0.0],"rotation":[0.0,0.0,0.0,1.0]},{"destroyable":false,"alone":false,"emissionUpEnabled":false,"emissionRightEnabled":false,"emissionLeftEnabled":false,"emissionDownEnabled":true,"position":[6.39995288848877,92.8000030517578,0.0],"rotation":[0.0,0.0,0.0,1.0]},{"destroyable":false,"alone":false,"emissionUpEnabled":false,"emissionRightEnabled":true,"emissionLeftEnabled":false,"emissionDownEnabled":true,"position":[9.59994983673096,92.8000030517578,0.0],"rotation":[0.0,0.0,0.0,1.0]},{"destroyable":false,"alone":false,"emissionUpEnabled":false,"emissionRightEnabled":true,"emissionLeftEnabled":false,"emissionDownEnabled":false,"position":[9.59994983673096,96.0,0.0],"rotation":[0.0,0.0,0.0,1.0]},{"destroyable":false,"alone":false,"emissionUpEnabled":true,"emissionRightEnabled":true,"emissionLeftEnabled":false,"emissionDownEnabled":false,"position":[9.59994983673096,99.1999969482422,0.0],"rotation":[0.0,0.0,0.0,1.0]},{"destroyable":false,"alone":false,"emissionUpEnabled":true,"emissionRightEnabled":false,"emissionLeftEnabled":false,"emissionDownEnabled":false,"position":[6.39995288848877,99.1999969482422,0.0],"rotation":[0.0,0.0,0.0,1.0]},{"destroyable":false,"alone":false,"emissionUpEnabled":false,"emissionRightEnabled":false,"emissionLeftEnabled":false,"emissionDownEnabled":false,"position":[3.199955701828,96.0,0.0],"rotation":[0.0,0.0,0.0,1.0]},{"destroyable":false,"alone":false,"emissionUpEnabled":false,"emissionRightEnabled":false,"emissionLeftEnabled":false,"emissionDownEnabled":false,"position":[-4.12464141845703E-05,96.0,0.0],"rotation":[0.0,0.0,0.0,1.0]},{"destroyable":false,"alone":false,"emissionUpEnabled":false,"emissionRightEnabled":false,"emissionLeftEnabled":false,"emissionDownEnabled":false,"position":[-3.20003819465637,96.0,0.0],"rotation":[0.0,0.0,0.0,1.0]},{"destroyable":false,"alone":false,"emissionUpEnabled":false,"emissionRightEnabled":false,"emissionLeftEnabled":false,"emissionDownEnabled":false,"position":[6.39995288848877,96.0,0.0],"rotation":[0.0,0.0,0.0,1.0]},{"destroyable":false,"alone":false,"emissionUpEnabled":true,"emissionRightEnabled":false,"emissionLeftEnabled":false,"emissionDownEnabled":false,"position":[3.199955701828,99.1999969482422,0.0],"rotation":[0.0,0.0,0.0,1.0]},{"destroyable":false,"alone":false,"emissionUpEnabled":true,"emissionRightEnabled":false,"emissionLeftEnabled":false,"emissionDownEnabled":false,"position":[-4.12464141845703E-05,99.1999969482422,0.0],"rotation":[0.0,0.0,0.0,1.0]},{"destroyable":false,"alone":false,"emissionUpEnabled":true,"emissionRightEnabled":false,"emissionLeftEnabled":false,"emissionDownEnabled":false,"position":[-3.20003819465637,99.1999969482422,0.0],"rotation":[0.0,0.0,0.0,1.0]},{"destroyable":false,"alone":false,"emissionUpEnabled":false,"emissionRightEnabled":true,"emissionLeftEnabled":false,"emissionDownEnabled":true,"position":[51.1999168395996,76.7999954223633,0.0],"rotation":[0.0,0.0,0.0,1.0]},{"destroyable":false,"alone":false,"emissionUpEnabled":true,"emissionRightEnabled":false,"emissionLeftEnabled":true,"emissionDownEnabled":true,"position":[47.9999198913574,76.7999954223633,0.0],"rotation":[0.0,0.0,0.0,1.0]}],"passableTileData":[{"destroyable":false,"alone":false,"emissionUpEnabled":true,"emissionRightEnabled":false,"emissionLeftEnabled":true,"emissionDownEnabled":true,"position":[-67.1999893188477,-102.399871826172,0.0],"rotation":[0.0,0.0,0.707106828689575,0.707106828689575]},{"destroyable":false,"alone":false,"emissionUpEnabled":true,"emissionRightEnabled":false,"emissionLeftEnabled":false,"emissionDownEnabled":true,"position":[-67.1999893188477,-99.1998748779297,0.0],"rotation":[0.0,0.0,0.707106828689575,0.707106828689575]},{"destroyable":false,"alone":false,"emissionUpEnabled":true,"emissionRightEnabled":false,"emissionLeftEnabled":false,"emissionDownEnabled":true,"position":[-67.1999893188477,-95.9998779296875,0.0],"rotation":[0.0,0.0,0.707106828689575,0.707106828689575]},{"destroyable":false,"alone":false,"emissionUpEnabled":true,"emissionRightEnabled":false,"emissionLeftEnabled":false,"emissionDownEnabled":true,"position":[-67.1999893188477,-92.7998809814453,0.0],"rotation":[0.0,0.0,0.707106828689575,0.707106828689575]},{"destroyable":false,"alone":false,"emissionUpEnabled":true,"emissionRightEnabled":true,"emissionLeftEnabled":false,"emissionDownEnabled":true,"position":[-67.1999893188477,-86.3998870849609,0.0],"rotation":[0.0,0.0,0.707106828689575,0.707106828689575]},{"destroyable":false,"alone":false,"emissionUpEnabled":true,"emissionRightEnabled":false,"emissionLeftEnabled":false,"emissionDownEnabled":true,"position":[-67.1999893188477,-89.5998840332031,0.0],"rotation":[0.0,0.0,0.707106828689575,0.707106828689575]}],"unifiedColliderData":[{"offset":[28.8000049591064,0.0],"size":[60.8000106811523,3.20000004768372],"tag":"Untagged","layer":11,"position":[-6.40003204345703,112.0,0.0],"rotation":[0.0,0.0,0.0,1.0]},{"offset":[8.0,0.0],"size":[19.2000007629395,3.20000004768372],"tag":"Untagged","layer":11,"position":[-6.40003490447998,99.1999969482422,0.0],"rotation":[0.0,0.0,0.0,1.0]},{"offset":[8.0,0.0],"size":[19.2000007629395,3.20000004768372],"tag":"Untagged","layer":11,"position":[-6.40003490447998,96.0,0.0],"rotation":[0.0,0.0,0.0,1.0]},{"offset":[8.0,0.0],"size":[19.2000007629395,3.20000004768372],"tag":"Untagged","layer":11,"position":[-6.40003490447998,92.8000030517578,0.0],"rotation":[0.0,0.0,0.0,1.0]},{"offset":[4.80000019073486,0.0],"size":[12.8000001907349,3.20000004768372],"tag":"Untagged","layer":11,"position":[-6.40003490447998,89.5999984741211,0.0],"rotation":[0.0,0.0,0.0,1.0]},{"offset":[4.80000019073486,0.0],"size":[12.8000001907349,3.20000004768372],"tag":"Untagged","layer":11,"position":[-6.40003490447998,86.3999938964844,0.0],"rotation":[0.0,0.0,0.0,1.0]},{"offset":[4.80000019073486,0.0],"size":[12.8000001907349,3.20000004768372],"tag":"Untagged","layer":11,"position":[-6.40003490447998,83.1999969482422,0.0],"rotation":[0.0,0.0,0.0,1.0]},{"offset":[1.60000002384186,0.0],"size":[6.40000009536743,3.20000004768372],"tag":"Untagged","layer":11,"position":[-6.40003490447998,80.0,0.0],"rotation":[0.0,0.0,0.0,1.0]},{"offset":[1.60000002384186,0.0],"size":[6.40000009536743,3.20000004768372],"tag":"Untagged","layer":11,"position":[-6.40003490447998,76.7999954223633,0.0],"rotation":[0.0,0.0,0.0,1.0]},{"offset":[1.60000002384186,0.0],"size":[6.40000009536743,3.20000004768372],"tag":"Untagged","layer":11,"position":[47.9999198913574,76.7999954223633,0.0],"rotation":[0.0,0.0,0.0,1.0]},{"offset":[1.60000002384186,0.0],"size":[6.40000009536743,3.20000004768372],"tag":"Untagged","layer":11,"position":[-6.40003490447998,73.5999908447266,0.0],"rotation":[0.0,0.0,0.0,1.0]},{"offset":[1.60000002384186,0.0],"size":[6.40000009536743,3.20000004768372],"tag":"Untagged","layer":11,"position":[92.7998809814453,73.5999908447266,0.0],"rotation":[0.0,0.0,0.0,1.0]},{"offset":[1.60000002384186,0.0],"size":[6.40000009536743,3.20000004768372],"tag":"Untagged","layer":11,"position":[-6.40003490447998,70.3999938964844,0.0],"rotation":[0.0,0.0,0.0,1.0]},{"offset":[1.60000002384186,0.0],"size":[6.40000009536743,3.20000004768372],"tag":"Untagged","layer":11,"position":[-6.40003490447998,54.3999900817871,0.0],"rotation":[0.0,0.0,0.0,1.0]},{"offset":[9.60000038146973,0.0],"size":[22.4000015258789,3.20000004768372],"tag":"Untagged","layer":11,"position":[15.9999513626099,54.3999900817871,0.0],"rotation":[0.0,0.0,0.0,1.0]},{"offset":[22.4000034332275,0.0],"size":[48.0000076293945,3.20000004768372],"tag":"Untagged","layer":11,"position":[-51.1999931335449,-15.9999465942383,0.0],"rotation":[0.0,0.0,0.0,1.0]},{"offset":[1.60000002384186,0.0],"size":[6.40000009536743,3.20000004768372],"tag":"Untagged","layer":11,"position":[-51.1999931335449,-35.1999359130859,0.0],"rotation":[0.0,0.0,0.0,1.0]},{"offset":[25.600004196167,0.0],"size":[54.4000091552734,3.20000004768372],"tag":"Untagged","layer":11,"position":[-32.0000114440918,-35.1999359130859,0.0],"rotation":[0.0,0.0,0.0,1.0]},{"offset":[30.4000053405762,0.0],"size":[64.0000076293945,3.20000004768372],"tag":"Untagged","layer":11,"position":[-112.0,-83.1998901367188,0.0],"rotation":[0.0,0.0,0.0,1.0]},{"offset":[41.5999946594238,0.0],"size":[86.3999862670898,3.20000004768372],"tag":"Untagged","layer":11,"position":[-112.0,-105.599868774414,0.0],"rotation":[0.0,0.0,0.0,1.0]},{"offset":[0.0,6.40000009536743],"size":[3.20000004768372,16.0],"tag":"Untagged","layer":11,"position":[92.7998809814453,60.799991607666,0.0],"rotation":[0.0,0.0,0.0,1.0]},{"offset":[0.0,8.0],"size":[3.20000004768372,19.2000007629395],"tag":"Untagged","layer":11,"position":[51.1999168395996,76.7999954223633,0.0],"rotation":[0.0,0.0,0.0,1.0]},{"offset":[0.0,44.799991607666],"size":[3.20000004768372,92.7999801635742],"tag":"Untagged","layer":11,"position":[19.1999473571777,-35.1999359130859,0.0],"rotation":[0.0,0.0,0.0,1.0]},{"offset":[0.0,3.20000004768372],"size":[3.20000004768372,9.60000038146973],"tag":"Untagged","layer":11,"position":[9.59994983673096,92.8000030517578,0.0],"rotation":[0.0,0.0,0.0,1.0]},{"offset":[0.0,3.20000004768372],"size":[3.20000004768372,9.60000038146973],"tag":"Untagged","layer":11,"position":[6.39995288848877,92.8000030517578,0.0],"rotation":[0.0,0.0,0.0,1.0]},{"offset":[0.0,8.0],"size":[3.20000004768372,19.2000007629395],"tag":"Untagged","layer":11,"position":[3.199955701828,83.1999969482422,0.0],"rotation":[0.0,0.0,0.0,1.0]},{"offset":[0.0,8.0],"size":[3.20000004768372,19.2000007629395],"tag":"Untagged","layer":11,"position":[-4.12464141845703E-05,83.1999969482422,0.0],"rotation":[0.0,0.0,0.0,1.0]},{"offset":[0.0,14.4000015258789],"size":[3.20000004768372,32.0000038146973],"tag":"Untagged","layer":11,"position":[-3.20003819465637,70.3999938964844,0.0],"rotation":[0.0,0.0,0.0,1.0]},{"offset":[0.0,62.399974822998],"size":[3.20000004768372,127.999946594238],"tag":"Untagged","layer":11,"position":[-6.40003490447998,-15.9999465942383,0.0],"rotation":[0.0,0.0,0.0,1.0]},{"offset":[0.0,35.2000007629395],"size":[3.20000004768372,73.5999984741211],"tag":"Untagged","layer":11,"position":[-28.8000144958496,-105.599868774414,0.0],"rotation":[0.0,0.0,0.0,1.0]},{"offset":[0.0,33.6000022888184],"size":[3.20000004768372,70.4000015258789],"tag":"Untagged","layer":11,"position":[-51.1999931335449,-83.1998901367188,0.0],"rotation":[0.0,0.0,0.0,1.0]},{"offset":[0.0,11.2000007629395],"size":[3.20000004768372,25.6000022888184],"tag":"Untagged","layer":11,"position":[-112.0,-105.599868774414,0.0],"rotation":[0.0,0.0,0.0,1.0]},{"offset":[8.0,0.0],"size":[19.2000007629395,1.39999997615814],"tag":"Passable","layer":11,"position":[-67.1999893188477,-102.399871826172,0.0],"rotation":[0.0,0.0,0.707106828689575,0.707106828689575]}],"movingPlatformData":[],"movingPlatformVerticalSpikesData":[{"platformType":"Vertical","waypointData":[{"index":0,"position":[-35.200008392334,-95.9998779296875,0.0],"rotation":[0.0,0.0,0.0,1.0]},{"index":1,"position":[-35.200008392334,-31.9999389648438,0.0],"rotation":[0.0,0.0,0.0,1.0]}],"speed":13.0,"waitTime":1.0,"startTime":1.5,"cyclic":false,"position":[-35.200008392334,-95.9998779296875,0.0],"rotation":[0.0,0.0,0.0,1.0]},{"platformType":"Vertical","waypointData":[{"index":0,"position":[12.7999467849731,-25.5999450683594,0.0],"rotation":[0.0,0.0,0.0,1.0]},{"index":1,"position":[12.7999467849731,54.3999938964844,0.0],"rotation":[0.0,0.0,0.0,1.0]}],"speed":13.0,"waitTime":1.0,"startTime":8.0,"cyclic":false,"position":[12.7999467849731,-25.5999450683594,0.0],"rotation":[0.0,0.0,0.0,1.0]}],"movingPlatformHorizontalSpikesData":[{"platformType":"Vertical","waypointData":[{"index":0,"position":[41.599925994873,57.5999908447266,0.0],"rotation":[0.0,0.0,0.0,1.0]},{"index":1,"position":[86.3998870849609,57.5999908447266,0.0],"rotation":[0.0,0.0,0.0,1.0]}],"speed":15.0,"waitTime":2.0,"startTime":0.0,"cyclic":false,"position":[41.599925994873,57.5999908447266,0.0],"rotation":[0.0,0.0,0.0,1.0]},{"platformType":"Vertical","waypointData":[{"index":0,"position":[86.3998870849609,73.5999908447266,0.0],"rotation":[0.0,0.0,0.0,1.0]},{"index":1,"position":[57.599910736084,92.8000030517578,0.0],"rotation":[0.0,0.0,0.0,1.0]}],"speed":17.0,"waitTime":1.5,"startTime":0.0,"cyclic":false,"position":[86.3998870849609,73.5999908447266,0.0],"rotation":[0.0,0.0,0.0,1.0]}],"sawData":[],"rayShooterData":[{"rayUp":true,"rayUpIntervalIntermittenceTime":0.0,"rayUpIntervalDurationTime":0.0,"rayRight":false,"rayRightIntervalIntermittenceTime":0.0,"rayRightIntervalDurationTime":0.0,"rayLeft":false,"rayLeftIntervalIntermittenceTime":0.0,"rayLeftIntervalDurationTime":0.0,"rayDown":false,"rayDownIntervalIntermittenceTime":0.0,"rayDownIntervalDurationTime":0.0,"rotationDirectionName":"Right","rotationDirectionIndex":0,"rotationSpeed":0.0,"waypointData":[],"speed":20.0,"waitTime":0.5,"startTime":0.0,"cyclic":false,"position":[-32.0000114440918,-102.399871826172,0.0],"rotation":[0.0,0.0,0.0,1.0]},{"rayUp":true,"rayUpIntervalIntermittenceTime":0.0,"rayUpIntervalDurationTime":0.0,"rayRight":false,"rayRightIntervalIntermittenceTime":0.0,"rayRightIntervalDurationTime":0.0,"rayLeft":false,"rayLeftIntervalIntermittenceTime":0.0,"rayLeftIntervalDurationTime":0.0,"rayDown":false,"rayDownIntervalIntermittenceTime":0.0,"rayDownIntervalDurationTime":0.0,"rotationDirectionName":"Right","rotationDirectionIndex":0,"rotationSpeed":0.0,"waypointData":[],"speed":20.0,"waitTime":0.5,"startTime":0.0,"cyclic":false,"position":[15.9999513626099,-31.9999389648438,0.0],"rotation":[0.0,0.0,0.0,1.0]}],"gravityChangerPlatformData":[{"nextGravityName":"Right","nextGravityIndex":1,"position":[49.0999183654785,89.5999984741211,0.0],"rotation":[0.0,0.0,0.707106828689575,0.707106828689575]}],"keyData":[],"lockedDoorData":[],"levelEndData":[{"position":[-106.699996948242,-95.9998779296875,0.0],"rotation":[0.0,0.0,0.707106828689575,-0.707106828689575]}],"spikeData":[{"typeName":"03","typeIndex":2,"position":[-83.1999969482422,-102.399871826172,0.0],"rotation":[0.0,0.0,0.0,1.0]},{"typeName":"03","typeIndex":2,"position":[-83.1999969482422,-86.3998870849609,0.0],"rotation":[0.0,0.0,1.0,0.0]},{"typeName":"03","typeIndex":2,"position":[-3.20003819465637,-15.9999465942383,0.0],"rotation":[0.0,0.0,0.707106828689575,-0.707106828689575]},{"typeName":"02","typeIndex":1,"position":[-3.20003819465637,-12.7999496459961,0.0],"rotation":[0.0,0.0,0.707106828689575,-0.707106828689575]},{"typeName":"02","typeIndex":1,"position":[-3.20003819465637,-9.59995269775391,0.0],"rotation":[0.0,0.0,0.707106828689575,-0.707106828689575]},{"typeName":"02","typeIndex":1,"position":[-3.20003819465637,-6.39995574951172,0.0],"rotation":[0.0,0.0,0.707106828689575,-0.707106828689575]},{"typeName":"02","typeIndex":1,"position":[-3.20003819465637,-3.19995880126953,0.0],"rotation":[0.0,0.0,0.707106828689575,-0.707106828689575]},{"typeName":"01","typeIndex":0,"position":[-3.20003819465637,3.814697265625E-05,0.0],"rotation":[0.0,0.0,0.707106828689575,-0.707106828689575]},{"typeName":"02","typeIndex":1,"position":[-3.20003819465637,3.20003509521484,0.0],"rotation":[0.0,0.0,0.707106828689575,-0.707106828689575]},{"typeName":"01","typeIndex":0,"position":[-3.20003819465637,6.40003204345703,0.0],"rotation":[0.0,0.0,0.707106828689575,-0.707106828689575]},{"typeName":"03","typeIndex":2,"position":[-3.20003819465637,9.60002899169922,0.0],"rotation":[0.0,0.0,0.707106828689575,-0.707106828689575]},{"typeName":"03","typeIndex":2,"position":[-3.20003819465637,12.8000259399414,0.0],"rotation":[0.0,0.0,0.707106828689575,-0.707106828689575]},{"typeName":"02","typeIndex":1,"position":[-3.20003819465637,16.0000228881836,0.0],"rotation":[0.0,0.0,0.707106828689575,-0.707106828689575]},{"typeName":"03","typeIndex":2,"position":[-3.20003819465637,19.2000198364258,0.0],"rotation":[0.0,0.0,0.707106828689575,-0.707106828689575]},{"typeName":"01","typeIndex":0,"position":[-3.20003819465637,22.400016784668,0.0],"rotation":[0.0,0.0,0.707106828689575,-0.707106828689575]},{"typeName":"02","typeIndex":1,"position":[-3.20003819465637,25.6000137329102,0.0],"rotation":[0.0,0.0,0.707106828689575,-0.707106828689575]},{"typeName":"01","typeIndex":0,"position":[-3.20003819465637,28.8000106811523,0.0],"rotation":[0.0,0.0,0.707106828689575,-0.707106828689575]},{"typeName":"01","typeIndex":0,"position":[-3.20003819465637,32.0000076293945,0.0],"rotation":[0.0,0.0,0.707106828689575,-0.707106828689575]},{"typeName":"01","typeIndex":0,"position":[-3.20003819465637,35.2000045776367,0.0],"rotation":[0.0,0.0,0.707106828689575,-0.707106828689575]},{"typeName":"01","typeIndex":0,"position":[-3.20003819465637,38.4000015258789,0.0],"rotation":[0.0,0.0,0.707106828689575,-0.707106828689575]},{"typeName":"01","typeIndex":0,"position":[-3.20003819465637,41.5999984741211,0.0],"rotation":[0.0,0.0,0.707106828689575,-0.707106828689575]},{"typeName":"03","typeIndex":2,"position":[-3.20003819465637,44.7999954223633,0.0],"rotation":[0.0,0.0,0.707106828689575,-0.707106828689575]},{"typeName":"01","typeIndex":0,"position":[-3.20003819465637,47.9999923706055,0.0],"rotation":[0.0,0.0,0.707106828689575,-0.707106828689575]},{"typeName":"01","typeIndex":0,"position":[-3.20003819465637,51.1999893188477,0.0],"rotation":[0.0,0.0,0.707106828689575,-0.707106828689575]},{"typeName":"02","typeIndex":1,"position":[54.3999176025391,112.0,0.0],"rotation":[0.0,0.0,0.707106828689575,-0.707106828689575]}],"collectableData":[{"position":[-41.6000022888184,-79.9998931884766,0.0],"rotation":[0.0,0.0,0.0,1.0]},{"position":[-41.6000022888184,-47.9999237060547,0.0],"rotation":[0.0,0.0,0.0,1.0]},{"position":[6.39995288848877,-3.19995880126953,0.0],"rotation":[0.0,0.0,0.0,1.0]},{"position":[6.39995288848877,38.4000015258789,0.0],"rotation":[0.0,0.0,0.0,1.0]},{"position":[-83.1999969482422,-92.7998809814453,0.0],"rotation":[0.0,0.0,0.0,1.0]},{"position":[-4.12464141845703E-05,105.599998474121,0.0],"rotation":[0.0,0.0,0.0,1.0]},{"position":[51.1999168395996,63.9999923706055,0.0],"rotation":[0.0,0.0,0.0,1.0]},{"position":[73.5998992919922,89.5999984741211,0.0],"rotation":[0.0,0.0,0.0,1.0]},{"position":[38.3999290466309,73.5999908447266,0.0],"rotation":[0.0,0.0,0.0,1.0]}]},{"playerData":[],"tileData":[],"passableTileData":[],"unifiedColliderData":[],"movingPlatformData":[],"movingPlatformVerticalSpikesData":[],"movingPlatformHorizontalSpikesData":[],"sawData":[],"rayShooterData":[],"gravityChangerPlatformData":[],"keyData":[],"lockedDoorData":[],"levelEndData":[],"spikeData":[],"collectableData":[]},{"playerData":[],"tileData":[],"passableTileData":[],"unifiedColliderData":[],"movingPlatformData":[],"movingPlatformVerticalSpikesData":[],"movingPlatformHorizontalSpikesData":[],"sawData":[],"rayShooterData":[],"gravityChangerPlatformData":[],"keyData":[],"lockedDoorData":[],"levelEndData":[],"spikeData":[],"collectableData":[]}]}